LICENSE
MANIFEST.in
NOTICE
README.rst
setup.py
bluevia/__init__.py
bluevia/api.py
bluevia/base_api.py
bluevia/exceptions.py
bluevia/utils.py
pyBlueVia.egg-info/PKG-INFO
pyBlueVia.egg-info/SOURCES.txt
pyBlueVia.egg-info/dependency_links.txt
pyBlueVia.egg-info/not-zip-safe
pyBlueVia.egg-info/requires.txt
pyBlueVia.egg-info/top_level.txt