Metadata-Version: 1.1
Name: pyBlueVia
Version: 0.1.0
Summary: A Python wrapper around the BlueVia API.
Home-page: https://pybluevia.readthedocs.org/
Author: Jose Antonio Rodríguez
Author-email: jarf@tid.es
License:    Copyright 2013 Telefonica Investigación y Desarrollo, S.A.U
